MANIFEST.in
README.md
requirements.txt
setup.cfg
setup.py
ni/__init__.py
ni.egg-info/PKG-INFO
ni.egg-info/SOURCES.txt
ni.egg-info/dependency_links.txt
ni.egg-info/requires.txt
ni.egg-info/top_level.txt