Metadata-Version: 1.1
Name: ni
Version: 0.0.1
Summary: A microservice-based web framework for Python.
Home-page: https://github.com/ojengwa/ni
Author: Bernard Ojengwa
Author-email: bernardojengwa@gmail.com
License: BSD
Download-URL: https://github.com/ojengwa/ni/tarball/0.0.1
Platform: UNKNOWN
Classifier: Development Status :: 3 - Alpha
Classifier: Intended Audience :: Developers
Classifier: Programming Language :: Python :: 3
